shuup_utils/__init__.py
shuup_utils/lang_constants.py
shuup_utils/setuptools/__init__.py
shuup_utils/setuptools/versions.py
shuup_utils/setuptools/commands/__init__.py
shuup_utils/setuptools/commands/build_static.py
shuup_utils/setuptools/commands/post_install.py
shuup_utils-0.7.0.0.dist-info/DESCRIPTION.rst
shuup_utils-0.7.0.0.dist-info/METADATA
shuup_utils-0.7.0.0.dist-info/RECORD
shuup_utils-0.7.0.0.dist-info/WHEEL
shuup_utils-0.7.0.0.dist-info/metadata.json
shuup_utils-0.7.0.0.dist-info/top_level.txt
