Metadata-Version: 2.0
Name: shuup-utils
Version: 0.7.0.0
Summary: Some personal dev utils for Shuup E-commerce Platform
Home-page: https://gitlab.com/nilit/shuup-utils
Author: UNKNOWN
Author-email: UNKNOWN
License: MIT
Keywords: shuup
Platform: UNKNOWN
Classifier: Development Status :: 3 - Alpha
Classifier: Framework :: Django :: 1.9
Classifier: Intended Audience :: Developers
Classifier: License :: OSI Approved :: MIT License
Classifier: Topic :: Software Development
Classifier: Programming Language :: Python :: 3
Classifier: Programming Language :: Python :: 3.5
Classifier: Topic :: Software Development :: Libraries :: Python Modules
Classifier: Topic :: Internet :: WWW/HTTP
Classifier: Topic :: Office/Business
Requires-Dist: shuup (==2.0)
Provides-Extra: dev
Requires-Dist: wheel (>=0.29.0); extra == 'dev'
Requires-Dist: twine (<2,>=1.8.1); extra == 'dev'
